gpt_vis/__init__.py
gpt_vis/api.py
gpt_vis/charts.py
gpt_vis/cli.py
gpt_vis-0.1.1.dist-info/METADATA
gpt_vis-0.1.1.dist-info/WHEEL
gpt_vis-0.1.1.dist-info/entry_points.txt
gpt_vis-0.1.1.dist-info/RECORD
