Metadata-Version: 2.3
Name: gpt-vis
Version: 0.1.1
Summary: A Python wrapper for gpt-vis-cli, enabling programmatic and command-line chart generation.
License: MIT
Keywords: visualization,charts,gpt,cli
Author: Gency Lee
Author-email: lichen900210@gmail.com
Requires-Python: >=3.8
Classifier: License :: OSI Approved :: MIT License
Classifier: Programming Language :: Python :: 3
Classifier: Programming Language :: Python :: 3.8
Classifier: Programming Language :: Python :: 3.9
Classifier: Programming Language :: Python :: 3.10
Classifier: Programming Language :: Python :: 3.11
Classifier: Programming Language :: Python :: 3.12
Classifier: Programming Language :: Python :: 3.13
Requires-Dist: pydantic (>=2.11.7,<3.0.0)
Project-URL: Homepage, https://github.com/JuneLeGency/gpt-vis-cli
Project-URL: Repository, https://github.com/JuneLeGency/gpt-vis-cli
